gon_pytorch/__init__.py
gon_pytorch/modules.py
gon_pytorch/utils.py
gon_pytorch-0.1.1.dist-info/LICENSE
gon_pytorch-0.1.1.dist-info/METADATA
gon_pytorch-0.1.1.dist-info/WHEEL
gon_pytorch-0.1.1.dist-info/top_level.txt
gon_pytorch-0.1.1.dist-info/RECORD
