Metadata-Version: 2.1
Name: gon-pytorch
Version: 0.1.1
Summary: Implementation of Gradient Origin Networks in PyTorch
Home-page: https://github.com/kklemon/gon-pytorch
Author: Kristian Klemon
Author-email: kristian.klemon@gmail.com
License: MIT
Keywords: artificial intelligence,deep learning
Platform: UNKNOWN
Requires-Dist: torch
